qmarkpg.py
setup.py
qmarkpg.egg-info/PKG-INFO
qmarkpg.egg-info/SOURCES.txt
qmarkpg.egg-info/dependency_links.txt
qmarkpg.egg-info/not-zip-safe
qmarkpg.egg-info/top_level.txt