Metadata-Version: 1.1
Name: qmarkpg
Version: 0.2
Summary: A psycopg2 wrapper using the qmark parameters style
Home-page: https://github.com/dvarrazzo/qmarkpg
Author: Daniele Varrazzo
Author-email: daniele.varrazzo@gmail.com
License: LGPL
Platform: UNKNOWN
Classifier: Development Status :: 4 - Beta
Classifier: Intended Audience :: Developers
Classifier: License :: OSI Approved :: GNU Library or Lesser General Public License (LGPL)
Classifier: Programming Language :: Python
Classifier: Programming Language :: Python :: 3
Classifier: Topic :: Database
Classifier: Topic :: Database :: Front-Ends
Classifier: Topic :: Software Development
Classifier: Topic :: Software Development :: Libraries :: Python Modules
